{
  "route": "/zh-hans/studio",
  "iteration": 1,
  "timestamp": "2026-04-22T10:31:18.206Z",
  "analysis": {
    "route": "/zh-hans/studio",
    "timestamp": "2026-04-22T10:31:18.206Z",
    "pages": 1,
    "aiReadyPages": 1,
    "probeSignals": 27,
    "capabilityJudgments": 5,
    "verifiedCapabilityJudgments": 5,
    "workflowPasses": 2,
    "workflowFailures": 0,
    "scriptAdjustments": 0,
    "openQuestions": 0,
    "nextProbeSuggestions": 1,
    "newFeatureHints": 12,
    "markdownMentions": 5,
    "apiMentions": 39,
    "scriptIds": [
      "page-navigation-zh-hans-studio"
    ]
  }
}